{
	"backtrace" : 1,
	"backtraceGraph" : 
	{
		"commands" : 
		[
			"add_custom_target"
		],
		"files" : 
		[
			"src/include/extlibs/cpr-master/deps/curl/CMakeLists.txt"
		],
		"nodes" : 
		[
			{
				"file" : 0
			},
			{
				"command" : 0,
				"file" : 0,
				"line" : 1703,
				"parent" : 0
			}
		]
	},
	"id" : "uninstall::@9f0cc5953bae75fb9cb3",
	"name" : "uninstall",
	"paths" : 
	{
		"build" : "src/include/extlibs/cpr-master/deps/curl",
		"source" : "src/include/extlibs/cpr-master/deps/curl"
	},
	"sourceGroups" : 
	[
		{
			"name" : "",
			"sourceIndexes" : 
			[
				0
			]
		},
		{
			"name" : "CMake Rules",
			"sourceIndexes" : 
			[
				1
			]
		}
	],
	"sources" : 
	[
		{
			"backtrace" : 1,
			"isGenerated" : true,
			"path" : "build/src/include/extlibs/cpr-master/deps/curl/CMakeFiles/uninstall",
			"sourceGroupIndex" : 0
		},
		{
			"backtrace" : 0,
			"isGenerated" : true,
			"path" : "build/src/include/extlibs/cpr-master/deps/curl/CMakeFiles/uninstall.rule",
			"sourceGroupIndex" : 1
		}
	],
	"type" : "UTILITY"
}
